osbpy/__init__.py
osbpy/osbpy.py
osbpy-3.0.1.dist-info/LICENSE
osbpy-3.0.1.dist-info/METADATA
osbpy-3.0.1.dist-info/WHEEL
osbpy-3.0.1.dist-info/top_level.txt
osbpy-3.0.1.dist-info/RECORD
