Metadata-Version: 2.1
Name: osbpy
Version: 3.0.1
Summary: Simple library for osu! storyboarding
Home-page: https://github.com/KawaiiWafu/osbpy
Author: Jiri Olszar
Author-email: remiliass@gmail.com
License: MIT
Keywords: graphics audio rhythm game
Platform: UNKNOWN
Classifier: Development Status :: 5 - Production/Stable
Classifier: Intended Audience :: Developers
Classifier: License :: OSI Approved :: MIT License
Classifier: Operating System :: OS Independent
Classifier: Programming Language :: Python
Classifier: Programming Language :: Python :: 3.7
Requires-Python: >=3
Requires-Dist: matplotlib (>=3.0.2)
Requires-Dist: numpy (>=1.15.4)
Requires-Dist: scipy (>=1.1.0)
